crawl4ai_mcp/__init__.py
crawl4ai_mcp/crawler.py
crawl4ai_mcp/fastmcp_server.py
crawl4ai_mcp/llm_config.py
crawl4ai_mcp/searcher.py
crawl_mcp-0.1.3.dist-info/METADATA
crawl_mcp-0.1.3.dist-info/WHEEL
crawl_mcp-0.1.3.dist-info/entry_points.txt
crawl_mcp-0.1.3.dist-info/licenses/LICENSE
crawl_mcp-0.1.3.dist-info/RECORD
