Metadata-Version: 2.4
Name: crawl_mcp
Version: 0.1.3
Summary: 基于 crawl4ai 和 FastMCP 的 MCP 服务器，提供网页爬取和 AI 分析功能
Project-URL: Homepage, https://github.com/gqy20/crawl-mcp
Project-URL: Repository, https://github.com/gqy20/crawl-mcp
Project-URL: Issues, https://github.com/gqy20/crawl-mcp/issues
Author: gqy20
License: MIT
License-File: LICENSE
Classifier: Development Status :: 3 - Alpha
Classifier: Intended Audience :: Developers
Classifier: License :: OSI Approved :: MIT License
Classifier: Programming Language :: Python :: 3
Classifier: Programming Language :: Python :: 3.12
Classifier: Programming Language :: Python :: 3.13
Requires-Python: >=3.12
Requires-Dist: beautifulsoup4>=4.13.5
Requires-Dist: crawl4ai>=0.7.8
Requires-Dist: ddgs>=9.0.0
Requires-Dist: fastmcp>=2.14.0
Requires-Dist: nest-asyncio>=1.6.0
Requires-Dist: openai>=2.0.0
